fair_research_login/__init__.py
fair_research_login/client.py
fair_research_login/code_handler.py
fair_research_login/exc.py
fair_research_login/local_server.py
fair_research_login/version.py
fair_research_login/token_storage/__init__.py
fair_research_login/token_storage/configparser_token_storage.py
fair_research_login/token_storage/json_token_storage.py
fair_research_login/token_storage/storage_tools.py
tests/__init__.py
tests/integration/__init__.py
tests/integration/conftest.py
tests/integration/test_client_refresh.py
tests/integration/test_login.py
tests/unit/__init__.py
tests/unit/conftest.py
tests/unit/mocks.py
tests/unit/test_client.py
tests/unit/test_code_handler.py
tests/unit/test_local_server.py
tests/unit/test_storage_classes.py
tests/unit/test_storage_tools.py
fair_research_login-0.3.1.dist-info/LICENSE
fair_research_login-0.3.1.dist-info/METADATA
fair_research_login-0.3.1.dist-info/WHEEL
fair_research_login-0.3.1.dist-info/top_level.txt
fair_research_login-0.3.1.dist-info/RECORD
