Metadata-Version: 2.1
Name: fair-research-login
Version: 0.3.1
Summary: A generalized library for storing native auth tokens
Home-page: https://github.com/fair-research/native-login
Maintainer: Fair Research
Maintainer-email: 
License: Apache 2.0
Classifier: Intended Audience :: Science/Research
Classifier: Intended Audience :: Developers
Classifier: License :: OSI Approved :: Apache Software License
Classifier: Operating System :: POSIX
Classifier: Operating System :: MacOS :: MacOS X
Classifier: Programming Language :: Python
Classifier: Programming Language :: Python :: 3.7
Classifier: Programming Language :: Python :: 3.8
Classifier: Programming Language :: Python :: 3.9
Classifier: Programming Language :: Python :: 3.10
Classifier: Programming Language :: Python :: 3.11
License-File: LICENSE
Requires-Dist: globus-sdk <4.0.0,>=3
